{
  "swagger": "2.0",
  "info": {
    "description": "Swagger API Doc",
    "title": "Swagger API",
    "termsOfService": "http://ip:port/**"
  },
  "paths": {
    "/system/user/deptTree": {
      "post": {
        "tags": [
          "用户信息"
        ],
        "summary": "获取部门树列表",
        "operationId": "deptTreeUsingPOST_1",
        "consumes": [
          "application/json"
        ],
        "produces": [
          "*/*"
        ],
        "parameters": [
          {
            "in": "body",
            "name": "reqDept",
            "description": "reqDept",
            "required": true,
            "schema": {
              "$ref": "#/definitions/Request«SysDeptBo»",
              "originalRef": "Request«SysDeptBo»"
            }
          }
        ],
        "responses": {
          "200": {
            "description": "OK",
            "schema": {
              "type": "array",
              "items": {
                "$ref": "#/definitions/Tree«long»",
                "originalRef": "Tree«long»"
              }
            }
          },
          "201": {
            "description": "Created"
          },
          "401": {
            "description": "Unauthorized"
          },
          "403": {
            "description": "Forbidden"
          },
          "404": {
            "description": "Not Found"
          }
        },
        "deprecated": false
      }
    }
  }
}